result/__init__.py
pytresult-1.0.2.dist-info/LICENSE
pytresult-1.0.2.dist-info/METADATA
pytresult-1.0.2.dist-info/WHEEL
pytresult-1.0.2.dist-info/RECORD
