Metadata-Version: 2.3
Name: pytresult
Version: 1.0.2
Summary: 
Author: Hícaro Dânrlley
Author-email: hdanrlley1@gmail.com
Requires-Python: >=3.12
Classifier: Programming Language :: Python :: 3
Classifier: Programming Language :: Python :: 3.12
Classifier: Programming Language :: Python :: 3.13
